sideninja/__init__.py
sideninja/__main__.py
sideninja-0.0.1.dist-info/LICENSE
sideninja-0.0.1.dist-info/METADATA
sideninja-0.0.1.dist-info/WHEEL
sideninja-0.0.1.dist-info/entry_points.txt
sideninja-0.0.1.dist-info/top_level.txt
sideninja-0.0.1.dist-info/RECORD
