Metadata-Version: 2.1
Name: sideninja
Version: 0.0.1
Summary: Ninja build file generator for PySide6, PyQt6, PySide2 and PyQt5
Home-page: https://github.com/mugiseyebrows/sideninja
Author: Stanislav Doronin
Author-email: mugisbrows@gmail.com
License-File: LICENSE
